[{"vinur_id":1,"fornafn":"Ruthie","eftirnafn":"Dietsche","netfang":"rdietsche0@dailymotion.com","heimilisfang":"2018 Dahle Terrace"},
{"vinur_id":2,"fornafn":"Erina","eftirnafn":"Cursons","netfang":"ecursons1@bizjournals.com","heimilisfang":"3998 Bluejay Hill"},
{"vinur_id":3,"fornafn":"Cleavland","eftirnafn":"Milsted","netfang":"cmilsted2@prweb.com","heimilisfang":"21223 Loftsgordon Pass"},
{"vinur_id":4,"fornafn":"Gwen","eftirnafn":"Van Waadenburg","netfang":"gvanwaadenburg3@icio.us"},
{"vinur_id":5,"fornafn":"Flint","eftirnafn":"Gregoretti","netfang":"fgregoretti4@icio.us","heimilisfang":"0961 Beilfuss Parkway"},
{"vinur_id":6,"fornafn":"Janka","eftirnafn":"Stratz","netfang":"jstratz5@trellian.com","heimilisfang":"245 Clove Trail"},
{"vinur_id":7,"fornafn":"Goraud","eftirnafn":"Bywaters","netfang":"gbywaters6@geocities.jp","heimilisfang":"03588 Oak Valley Court","lanasafn":[{"bok_id":946,"bok_lanadagsetning":"2017-08-09"},{"bok_id":19,"bok_lanadagsetning":"2016-09-12"},{"bok_id":931,"bok_lanadagsetning":"2017-05-29"}]},
{"vinur_id":8,"fornafn":"Dan","eftirnafn":"Beyn","netfang":"dbeyn7@shop-pro.jp"},
{"vinur_id":9,"fornafn":"Royce","eftirnafn":"Flaunders","netfang":"rflaunders8@photobucket.com","heimilisfang":"92582 Union Hill"},
{"vinur_id":10,"fornafn":"Nancey","eftirnafn":"Munt","netfang":"nmunt9@furl.net","heimilisfang":"41291 Autumn Leaf Junction","lanasafn":[{"bok_id":657,"bok_lanadagsetning":"2017-03-31"},{"bok_id":368,"bok_lanadagsetning":"2016-09-21"}]},
{"vinur_id":11,"fornafn":"Creighton","eftirnafn":"Kitt","netfang":"ckitta@discuz.net","heimilisfang":"849 Tony Circle"},
{"vinur_id":12,"fornafn":"Gerri","eftirnafn":"Calfe","netfang":"gcalfeb@behance.net","heimilisfang":"34 Sullivan Place"},
{"vinur_id":13,"fornafn":"Nicoli","eftirnafn":"Quakley","netfang":"nquakleyc@nps.gov","heimilisfang":"11289 Briar Crest Road"},
{"vinur_id":14,"fornafn":"Winny","eftirnafn":"Dresser","netfang":"wdresserd@bandcamp.com"},
{"vinur_id":15,"fornafn":"Egon","eftirnafn":"Buckbee","netfang":"ebuckbeee@yahoo.com","heimilisfang":"42 Charing Cross Pass"},
{"vinur_id":16,"fornafn":"Fidelia","eftirnafn":"Lemmers","netfang":"flemmersf@jimdo.com","heimilisfang":"02 Esch Junction"},
{"vinur_id":17,"fornafn":"Ardella","eftirnafn":"Niave","netfang":"aniaveg@dot.gov","heimilisfang":"0566 Monument Circle","lanasafn":[{"bok_id":59,"bok_lanadagsetning":"2016-11-07"},{"bok_id":126,"bok_lanadagsetning":"2017-08-04"},{"bok_id":275,"bok_lanadagsetning":"2017-04-11"}]},
{"vinur_id":18,"fornafn":"Worthington","eftirnafn":"Goering","netfang":"wgoeringh@php.net","heimilisfang":"50640 Bartillon Circle"},
{"vinur_id":19,"fornafn":"Solly","eftirnafn":"Andrzejowski","netfang":"sandrzejowskii@hp.com","heimilisfang":"2 Fairview Avenue","lanasafn":[{"bok_id":370,"bok_lanadagsetning":"2016-10-26"},{"bok_id":862,"bok_lanadagsetning":"2016-09-19"},{"bok_id":666,"bok_lanadagsetning":"2016-09-04"}]},
{"vinur_id":20,"fornafn":"Briny","eftirnafn":"Fullagar","netfang":"bfullagarj@imageshack.us","heimilisfang":"344 Elka Center"},
{"vinur_id":21,"fornafn":"Deirdre","eftirnafn":"MacIntyre","netfang":"dmacintyrek@prlog.org","heimilisfang":"8 Northfield Parkway","lanasafn":[{"bok_id":171,"bok_lanadagsetning":"2016-11-17"},{"bok_id":688,"bok_lanadagsetning":"2017-07-20"},{"bok_id":84,"bok_lanadagsetning":"2017-02-27"}]},
{"vinur_id":22,"fornafn":"Ulberto","eftirnafn":"Fetherston","netfang":"ufetherstonl@hao123.com","heimilisfang":"48 Anniversary Junction","lanasafn":[{"bok_id":904,"bok_lanadagsetning":"2017-03-03"}]},
{"vinur_id":23,"fornafn":"Marylee","eftirnafn":"Mardell","netfang":"mmardellm@microsoft.com","heimilisfang":"8910 7th Park","lanasafn":[{"bok_id":500,"bok_lanadagsetning":"2017-05-23"},{"bok_id":741,"bok_lanadagsetning":"2016-10-29"}]},
{"vinur_id":24,"fornafn":"Giana","eftirnafn":"Fergusson","netfang":"gfergussonn@google.ru","heimilisfang":"15 Havey Lane"},
{"vinur_id":25,"fornafn":"West","eftirnafn":"McLellan","netfang":"wmclellano@skyrock.com","heimilisfang":"93265 Armistice Crossing"},
{"vinur_id":26,"fornafn":"Raychel","eftirnafn":"Prew","netfang":"rprewp@eepurl.com","heimilisfang":"58195 Logan Center"},
{"vinur_id":27,"fornafn":"Gilberta","eftirnafn":"Lace","netfang":"glaceq@tiny.cc","heimilisfang":"86 Dennis Terrace","lanasafn":[{"bok_id":818,"bok_lanadagsetning":"2017-02-26"},{"bok_id":65,"bok_lanadagsetning":"2016-11-02"},{"bok_id":548,"bok_lanadagsetning":"2016-09-18"}]},
{"vinur_id":28,"fornafn":"Wyn","eftirnafn":"Clemendet","netfang":"wclemendetr@uiuc.edu","heimilisfang":"816 Butterfield Park"},
{"vinur_id":29,"fornafn":"Cati","eftirnafn":"Guilbert","netfang":"cguilberts@wunderground.com","heimilisfang":"7 Manitowish Crossing"},
{"vinur_id":30,"fornafn":"Norrie","eftirnafn":"Wenderoth","netfang":"nwenderotht@nydailynews.com"},
{"vinur_id":31,"fornafn":"Ulberto","eftirnafn":"Domican","netfang":"udomicanu@chron.com","heimilisfang":"8 Hoard Point"},
{"vinur_id":32,"fornafn":"Annalise","eftirnafn":"Stelli","netfang":"astelliv@yandex.ru","heimilisfang":"162 Garrison Road"},
{"vinur_id":33,"fornafn":"Jenine","eftirnafn":"Jovis","netfang":"jjovisw@craigslist.org","heimilisfang":"59225 Clarendon Court"},
{"vinur_id":34,"fornafn":"Penny","eftirnafn":"Pascoe","netfang":"ppascoex@360.cn","heimilisfang":"43939 Linden Junction","lanasafn":[{"bok_id":202,"bok_lanadagsetning":"2017-07-13"},{"bok_id":28,"bok_lanadagsetning":"2016-09-07"},{"bok_id":693,"bok_lanadagsetning":"2017-01-05"}]},
{"vinur_id":35,"fornafn":"Alessandra","eftirnafn":"Toghill","netfang":"atoghilly@go.com","heimilisfang":"17 Clyde Gallagher Street"},
{"vinur_id":36,"fornafn":"Kat","eftirnafn":"Pinock","netfang":"kpinockz@diigo.com","heimilisfang":"11 Merchant Junction"},
{"vinur_id":37,"fornafn":"Bartholomew","eftirnafn":"Lippard","netfang":"blippard10@wikimedia.org","heimilisfang":"25888 Grover Avenue"},
{"vinur_id":38,"fornafn":"Maynard","eftirnafn":"Nijssen","netfang":"mnijssen11@cargocollective.com"},
{"vinur_id":39,"fornafn":"Drusie","eftirnafn":"Rome","netfang":"drome12@msn.com","heimilisfang":"789 Service Drive"},
{"vinur_id":40,"fornafn":"Kirbie","eftirnafn":"Hallaways","netfang":"khallaways13@alexa.com","heimilisfang":"1 Golden Leaf Terrace"},
{"vinur_id":41,"fornafn":"Sydney","eftirnafn":"Connar","netfang":"sconnar14@miitbeian.gov.cn","heimilisfang":"71 Sherman Park"},
{"vinur_id":42,"fornafn":"Marla","eftirnafn":"Bezants","netfang":"mbezants15@amazon.com"},
{"vinur_id":43,"fornafn":"Krista","eftirnafn":"Domenge","netfang":"kdomenge16@qq.com","heimilisfang":"3 Dunning Park"},
{"vinur_id":44,"fornafn":"Moll","eftirnafn":"Shird","netfang":"mshird17@oracle.com","heimilisfang":"1747 Vera Center"},
{"vinur_id":45,"fornafn":"Mayor","eftirnafn":"Mosby","netfang":"mmosby18@mit.edu","heimilisfang":"6452 Reinke Terrace","lanasafn":[{"bok_id":259,"bok_lanadagsetning":"2016-11-05"},{"bok_id":725,"bok_lanadagsetning":"2016-10-20"}]},
{"vinur_id":46,"fornafn":"Kanya","eftirnafn":"Lanning","netfang":"klanning19@nasa.gov","heimilisfang":"01 Kensington Park"},
{"vinur_id":47,"fornafn":"Ryley","eftirnafn":"Francesco","netfang":"rfrancesco1a@sciencedirect.com"},
{"vinur_id":48,"fornafn":"Shannon","eftirnafn":"Manjin","netfang":"smanjin1b@dell.com","heimilisfang":"150 Crescent Oaks Hill"},
{"vinur_id":49,"fornafn":"Doralynne","eftirnafn":"Egerton","netfang":"degerton1c@blogs.com","heimilisfang":"1858 Pearson Way"},
{"vinur_id":50,"fornafn":"Harrietta","eftirnafn":"Durn","netfang":"hdurn1d@sourceforge.net","heimilisfang":"44 Talmadge Center"},
{"vinur_id":51,"fornafn":"Clywd","eftirnafn":"Mersh","netfang":"cmersh1e@t.co","heimilisfang":"0730 Independence Point"},
{"vinur_id":52,"fornafn":"Marysa","eftirnafn":"Hilling","netfang":"mhilling1f@sun.com","heimilisfang":"68295 Cherokee Alley"},
{"vinur_id":53,"fornafn":"Marietta","eftirnafn":"Landsborough","netfang":"mlandsborough1g@marketwatch.com","heimilisfang":"4 Kedzie Drive"},
{"vinur_id":54,"fornafn":"Rahel","eftirnafn":"Powell","netfang":"rpowell1h@salon.com","lanasafn":[{"bok_id":875,"bok_lanadagsetning":"2016-11-13"},{"bok_id":125,"bok_lanadagsetning":"2017-02-23"}]},
{"vinur_id":55,"fornafn":"Marylou","eftirnafn":"Birkby","netfang":"mbirkby1i@feedburner.com","heimilisfang":"85 Talisman Drive"},
{"vinur_id":56,"fornafn":"Ilene","eftirnafn":"Chester","netfang":"ichester1j@bluehost.com","heimilisfang":"7131 Elgar Road"},
{"vinur_id":57,"fornafn":"Lucio","eftirnafn":"Bortolutti","netfang":"lbortolutti1k@behance.net","heimilisfang":"01 Shelley Alley"},
{"vinur_id":58,"fornafn":"Anna","eftirnafn":"Loffill","netfang":"aloffill1l@infoseek.co.jp","heimilisfang":"5 Di Loreto Park"},
{"vinur_id":59,"fornafn":"Kearney","eftirnafn":"Fullard","netfang":"kfullard1m@51.la","heimilisfang":"62 Calypso Junction"},
{"vinur_id":60,"fornafn":"Aarika","eftirnafn":"Zealey","netfang":"azealey1n@go.com","heimilisfang":"5 Fuller Road"},
{"vinur_id":61,"fornafn":"Nicola","eftirnafn":"Matteotti","netfang":"nmatteotti1o@bandcamp.com","heimilisfang":"59865 Haas Terrace"},
{"vinur_id":62,"fornafn":"Hagan","eftirnafn":"Raithmill","netfang":"hraithmill1p@weather.com","heimilisfang":"072 Dexter Alley"},
{"vinur_id":63,"fornafn":"Avery","eftirnafn":"Viccary","netfang":"aviccary1q@auda.org.au","heimilisfang":"41 Helena Park"},
{"vinur_id":64,"fornafn":"Isidoro","eftirnafn":"O'Gavin","netfang":"iogavin1r@auda.org.au","heimilisfang":"47 Heath Crossing"},
{"vinur_id":65,"fornafn":"Kamila","eftirnafn":"Baiyle","netfang":"kbaiyle1s@statcounter.com","heimilisfang":"3086 Dayton Road"},
{"vinur_id":66,"fornafn":"Abbye","eftirnafn":"Westgarth","netfang":"awestgarth1t@istockphoto.com","heimilisfang":"6559 Packers Pass"},
{"vinur_id":67,"fornafn":"Courtney","eftirnafn":"Treharne","netfang":"ctreharne1u@list-manage.com","heimilisfang":"81 Petterle Terrace"},
{"vinur_id":68,"fornafn":"Quinta","eftirnafn":"Despenser","netfang":"qdespenser1v@state.gov","heimilisfang":"56439 Waywood Drive","lanasafn":[{"bok_id":12,"bok_lanadagsetning":"2017-06-05"}]},
{"vinur_id":69,"fornafn":"Dareen","eftirnafn":"Sorrill","netfang":"dsorrill1w@wunderground.com","heimilisfang":"0 Independence Parkway"},
{"vinur_id":70,"fornafn":"Herculie","eftirnafn":"Thames","netfang":"hthames1x@facebook.com","heimilisfang":"649 Hanson Street"},
{"vinur_id":71,"fornafn":"Weider","eftirnafn":"Midson","netfang":"wmidson1y@blogspot.com","heimilisfang":"550 Karstens Avenue"},
{"vinur_id":72,"fornafn":"Ferdinanda","eftirnafn":"Hacket","netfang":"fhacket1z@hostgator.com","heimilisfang":"1615 Lakewood Gardens Pass"},
{"vinur_id":73,"fornafn":"Dallon","eftirnafn":"Thurgood","netfang":"dthurgood20@taobao.com","heimilisfang":"2 Randy Drive"},
{"vinur_id":74,"fornafn":"Jeannette","eftirnafn":"Senner","netfang":"jsenner21@virginia.edu","heimilisfang":"09688 Vidon Circle","lanasafn":[{"bok_id":295,"bok_lanadagsetning":"2016-11-02"},{"bok_id":154,"bok_lanadagsetning":"2017-05-01"}]},
{"vinur_id":75,"fornafn":"Aldrich","eftirnafn":"Austen","netfang":"aausten22@is.gd","heimilisfang":"82 Grayhawk Hill"},
{"vinur_id":76,"fornafn":"Reagen","eftirnafn":"Deeson","netfang":"rdeeson23@people.com.cn","heimilisfang":"57 Monterey Circle","lanasafn":[{"bok_id":216,"bok_lanadagsetning":"2017-02-03"},{"bok_id":430,"bok_lanadagsetning":"2017-06-25"},{"bok_id":305,"bok_lanadagsetning":"2016-09-13"}]},
{"vinur_id":77,"fornafn":"Dianne","eftirnafn":"Padbury","netfang":"dpadbury24@wikipedia.org","heimilisfang":"097 Monument Avenue","lanasafn":[{"bok_id":977,"bok_lanadagsetning":"2016-12-15"},{"bok_id":606,"bok_lanadagsetning":"2017-02-18"}]},
{"vinur_id":78,"fornafn":"Erhart","eftirnafn":"Mercik","netfang":"emercik25@wiley.com","heimilisfang":"69604 South Point","lanasafn":[{"bok_id":868,"bok_lanadagsetning":"2016-10-17"}]},
{"vinur_id":79,"fornafn":"Haze","eftirnafn":"Gully","netfang":"hgully26@nps.gov","heimilisfang":"30 Fair Oaks Road","lanasafn":[{"bok_id":208,"bok_lanadagsetning":"2017-04-08"},{"bok_id":725,"bok_lanadagsetning":"2017-09-02"},{"bok_id":732,"bok_lanadagsetning":"2016-10-14"}]},
{"vinur_id":80,"fornafn":"Kathlin","eftirnafn":"Hackney","netfang":"khackney27@spiegel.de","heimilisfang":"29676 Cordelia Trail","lanasafn":[{"bok_id":264,"bok_lanadagsetning":"2017-04-29"}]},
{"vinur_id":81,"fornafn":"Rosabelle","eftirnafn":"Berfoot","netfang":"rberfoot28@bbc.co.uk","heimilisfang":"5606 Ruskin Point"},
{"vinur_id":82,"fornafn":"Edik","eftirnafn":"Roskams","netfang":"eroskams29@livejournal.com","heimilisfang":"44 Browning Drive","lanasafn":[{"bok_id":226,"bok_lanadagsetning":"2017-05-13"},{"bok_id":126,"bok_lanadagsetning":"2016-12-05"}]},
{"vinur_id":83,"fornafn":"Ethe","eftirnafn":"Shoesmith","netfang":"eshoesmith2a@senate.gov","lanasafn":[{"bok_id":851,"bok_lanadagsetning":"2017-04-16"},{"bok_id":421,"bok_lanadagsetning":"2016-10-23"},{"bok_id":438,"bok_lanadagsetning":"2017-05-19"}]},
{"vinur_id":84,"fornafn":"Riane","eftirnafn":"Tippin","netfang":"rtippin2b@examiner.com","heimilisfang":"1 Havey Court"},
{"vinur_id":85,"fornafn":"Konrad","eftirnafn":"Bullock","netfang":"kbullock2c@paginegialle.it","heimilisfang":"36 Green Plaza"},
{"vinur_id":86,"fornafn":"Zachery","eftirnafn":"Glenny","netfang":"zglenny2d@china.com.cn","heimilisfang":"80609 Londonderry Lane"},
{"vinur_id":87,"fornafn":"Estell","eftirnafn":"Guillond","netfang":"eguillond2e@ebay.com","heimilisfang":"74 Jay Pass"},
{"vinur_id":88,"fornafn":"Harrie","eftirnafn":"Derks","netfang":"hderks2f@skyrock.com","heimilisfang":"60491 Arapahoe Place"},
{"vinur_id":89,"fornafn":"Archer","eftirnafn":"Baraja","netfang":"abaraja2g@boston.com","heimilisfang":"88070 Bultman Crossing"},
{"vinur_id":90,"fornafn":"Chet","eftirnafn":"Bridgens","netfang":"cbridgens2h@twitpic.com","heimilisfang":"04972 Declaration Way","lanasafn":[{"bok_id":410,"bok_lanadagsetning":"2016-12-14"},{"bok_id":685,"bok_lanadagsetning":"2017-04-26"}]},
{"vinur_id":91,"fornafn":"Glenden","eftirnafn":"Erdely","netfang":"gerdely2i@google.co.jp","heimilisfang":"3269 Linden Court"},
{"vinur_id":92,"fornafn":"Carole","eftirnafn":"Coupe","netfang":"ccoupe2j@shareasale.com","heimilisfang":"090 Milwaukee Alley","lanasafn":[{"bok_id":776,"bok_lanadagsetning":"2016-11-07"},{"bok_id":734,"bok_lanadagsetning":"2017-03-23"}]},
{"vinur_id":93,"fornafn":"Opaline","eftirnafn":"Anglin","netfang":"oanglin2k@tinyurl.com","heimilisfang":"365 Katie Hill"},
{"vinur_id":94,"fornafn":"Elyssa","eftirnafn":"Bowld","netfang":"ebowld2l@cnet.com","heimilisfang":"7 Talisman Hill"},
{"vinur_id":95,"fornafn":"Ambros","eftirnafn":"Fussey","netfang":"afussey2m@vistaprint.com","heimilisfang":"17995 Granby Lane","lanasafn":[{"bok_id":886,"bok_lanadagsetning":"2017-01-17"},{"bok_id":332,"bok_lanadagsetning":"2017-06-15"},{"bok_id":163,"bok_lanadagsetning":"2017-08-21"}]},
{"vinur_id":96,"fornafn":"Lanie","eftirnafn":"Hickin","netfang":"lhickin2n@auda.org.au","heimilisfang":"0119 Schiller Terrace"},
{"vinur_id":97,"fornafn":"Marianna","eftirnafn":"Warrack","netfang":"mwarrack2o@feedburner.com","heimilisfang":"4 Green Ridge Lane","lanasafn":[{"bok_id":162,"bok_lanadagsetning":"2017-04-28"}]},
{"vinur_id":98,"fornafn":"Cathy","eftirnafn":"Rubinlicht","netfang":"crubinlicht2p@cyberchimps.com","heimilisfang":"7 Butterfield Road","lanasafn":[{"bok_id":93,"bok_lanadagsetning":"2017-05-04"},{"bok_id":958,"bok_lanadagsetning":"2016-11-19"},{"bok_id":901,"bok_lanadagsetning":"2017-05-20"}]},
{"vinur_id":99,"fornafn":"Gale","eftirnafn":"Ballach","netfang":"gballach2q@google.cn","heimilisfang":"9 Killdeer Way","lanasafn":[{"bok_id":650,"bok_lanadagsetning":"2016-10-09"}]},
{"vinur_id":100,"fornafn":"Dar","eftirnafn":"Ramsted","netfang":"dramsted2r@dell.com","heimilisfang":"60 Forest Plaza"}]